<?xml version="1.0" encoding="utf-8" ?>
<dwsync>
<file name="banner.jpg" server="www.lynup.com" local="130479778820000000" remote="130506127800000000" Dst="2" />
<file name="client-logo1.png" server="www.lynup.com" local="130479778820000000" remote="130506127800000000" Dst="2" />
<file name="client-logo2.png" server="www.lynup.com" local="130479778840000000" remote="130506127800000000" Dst="2" />
<file name="client-logo3.png" server="www.lynup.com" local="130479778840000000" remote="130506127800000000" Dst="2" />
<file name="client-logo4.png" server="www.lynup.com" local="130479778840000000" remote="130506127800000000" Dst="2" />
<file name="lindsayGrenfell.jpg" server="www.lynup.com" local="130479778840000000" remote="130506127800000000" Dst="2" />
<file name="slide-bg-sm.jpg" server="www.lynup.com" local="130479778840000000" remote="130506127800000000" Dst="2" />
<file name="slide-bg.jpg" server="www.lynup.com" local="130479778860000000" remote="130506127800000000" Dst="2" />
<file name="slide1.jpg" server="www.lynup.com" local="130479778860000000" remote="130506127800000000" Dst="2" />
<file name="title-slide1.jpg" server="www.lynup.com" local="130479778880000000" remote="130506127800000000" Dst="2" />
<file name="slide2.jpg" server="www.lynup.com" local="130479778860000000" remote="130506127800000000" Dst="2" />
<file name="title-slide2.jpg" server="www.lynup.com" local="130479778880000000" remote="130506127800000000" Dst="2" />
</dwsync>